[{
    "table": [
        {
            "cardinal_points": "10 : 2",
            "club": "TSV Waldkirchen",
            "max_score": "419.4",
            "place": "1",
            "score": "2366.4 : 2190.4"
        },
        {
            "cardinal_points": "8 : 4",
            "club": "ESV M\u00fcnchen-Neuaubing",
            "max_score": "470.8",
            "place": "2",
            "score": "2385.4 : 2189"
        },
        {
            "cardinal_points": "6 : 6",
            "club": "KSV Kitzingen",
            "max_score": "453.6",
            "place": "3",
            "score": "2316 : 2194.8"
        },
        {
            "cardinal_points": "0 : 12",
            "club": "Eichenauer SV",
            "max_score": "356.0",
            "place": "4",
            "score": "1878 : 2371.6"
        }
    ]
}]