[{
    "table": [
        {
            "cardinal_points": "18 : 3",
            "club": "TB 03 Roding II",
            "max_score": "539.6",
            "place": "1",
            "score": "3365.1 : 2691.6"
        },
        {
            "cardinal_points": "15 : 6",
            "club": "AC Suhl",
            "max_score": "503.0",
            "place": "2",
            "score": "3177.7 : 3073.9"
        },
        {
            "cardinal_points": "11 : 10",
            "club": "SV90 Gr\u00e4fenroda",
            "max_score": "473.3",
            "place": "3",
            "score": "3212.4 : 2857.6"
        },
        {
            "cardinal_points": "10 : 14",
            "club": "KSV Langen",
            "max_score": "500.0",
            "place": "4",
            "score": "3571 : 3299.1"
        },
        {
            "cardinal_points": "0 : 21",
            "club": "FTG Pfungstadt",
            "max_score": "286.2",
            "place": "5",
            "score": "1591.7 : 2995.7"
        }
    ]
}]