[{
    "scheduled_competitions": [
        {
            "date": "02.04.2016",
            "guest": "SV Germania Obrigheim II",
            "home": "KSV L\u00f6rrach",
            "location": "L\u00f6rrach-Haagen",
            "time": "19:00"
        },
        {
            "date": "02.04.2016",
            "guest": "KSC Schifferstadt",
            "home": "AC Weinheim",
            "location": "Weinheim",
            "time": "19:00"
        },
        {
            "date": "23.04.2016",
            "guest": "SC Pforzheim",
            "home": "SV Germania Obrigheim II",
            "location": "Obrigheim",
            "time": "19:00"
        },
        {
            "date": "23.04.2016",
            "guest": "KSV L\u00f6rrach",
            "home": "KSC Schifferstadt",
            "location": "Schifferstadt",
            "time": "18:00"
        }
    ]
}]