[{
    "competitions": [
        {
            "date": "08.03.2014",
            "guest": "Berliner TSC",
            "home": "SV Germania Obrigheim",
            "location": "Obrigheim",
            "score": "926.0 : 785.4",
            "url": "https://www.iat.uni-leipzig.de/datenbanken/blgew1314/start.php?pid='123'&protokoll=1&wkid=AA5EEAF4B7C44E908181DAF0F40D35F1"
        },
        {
            "date": "08.03.2014",
            "guest": "Chemnitzer AC",
            "home": "KSV Durlach",
            "location": "Karlsruhe-Durlach",
            "score": "805.8 : 870.2",
            "url": "https://www.iat.uni-leipzig.de/datenbanken/blgew1314/start.php?pid='123'&protokoll=1&wkid=5D13947AE5E84B9E9938EC2C35EE5E32"
        },
        {
            "date": "08.03.2014",
            "guest": "SSV Samswegen",
            "home": "AC Germania St.Ilgen",
            "location": "Leimen-St Ilgen",
            "score": "752.0 : 654.0",
            "url": "https://www.iat.uni-leipzig.de/datenbanken/blgew1314/start.php?pid='123'&protokoll=1&wkid=97870675487C4A648534D4CC93DB43EA"
        },
        {
            "date": "08.03.2014",
            "guest": "Oder-Sund Team",
            "home": "AV Speyer 03",
            "location": "Speyer",
            "score": "835.4 : 723.8",
            "url": "https://www.iat.uni-leipzig.de/datenbanken/blgew1314/start.php?pid='123'&protokoll=1&wkid=B81820FD244B4BC6B5522C282F199727"
        },
        {
            "date": "08.03.2014",
            "guest": "SG Fortschritt Eibau",
            "home": "AC Mutterstadt",
            "location": "Mutterstadt",
            "score": "770.4 : 385.8",
            "url": "https://www.iat.uni-leipzig.de/datenbanken/blgew1314/start.php?pid='123'&protokoll=1&wkid=38D382D722FE4CE3821D735C3AA97589"
        },
        {
            "date": "08.03.2014",
            "guest": "KG G\u00f6rlitz-Zittau",
            "home": "TB 03 Roding",
            "location": "Roding",
            "score": "784.0 : 455.6",
            "url": "https://www.iat.uni-leipzig.de/datenbanken/blgew1314/start.php?pid='123'&protokoll=1&wkid=279B7BB937254D8F906B3E66DB724F23"
        },
        {
            "date": "22.02.2014",
            "guest": "TSV Heinsheim",
            "home": "AV Speyer 03",
            "location": "Speyer",
            "score": "743.1 : 583.2",
            "url": "https://www.iat.uni-leipzig.de/datenbanken/blgew1314/start.php?pid='123'&protokoll=1&wkid=3D2BF1498C0C4B37A0B2FC3803C08820"
        },
        {
            "date": "22.02.2014",
            "guest": "KSV Durlach",
            "home": "AC Germania St.Ilgen",
            "location": "Leimen-St Ilgen",
            "score": "733.0 : 783.8",
            "url": "https://www.iat.uni-leipzig.de/datenbanken/blgew1314/start.php?pid='123'&protokoll=1&wkid=7FB1418D5672427BAE3D0070D97471FD"
        },
        {
            "date": "22.02.2014",
            "guest": "AC Mutterstadt",
            "home": "TB 03 Roding",
            "location": "Roding",
            "score": "718.3 : 743.8",
            "url": "https://www.iat.uni-leipzig.de/datenbanken/blgew1314/start.php?pid='123'&protokoll=1&wkid=4885428FF99B4DA6B58C9D01DA60735B"
        },
        {
            "date": "25.01.2014",
            "guest": "TB 03 Roding",
            "home": "SV Germania Obrigheim",
            "location": "Obrigheim",
            "score": "760.4 : 699.6",
            "url": "https://www.iat.uni-leipzig.de/datenbanken/blgew1314/start.php?pid='123'&protokoll=1&wkid=FE14A15492924117AEA5CB186F5004A5"
        },
        {
            "date": "25.01.2014",
            "guest": "AC Germania St.Ilgen",
            "home": "TSV Heinsheim",
            "location": "Bad Rappenau",
            "score": "610.0 : 648.9",
            "url": "https://www.iat.uni-leipzig.de/datenbanken/blgew1314/start.php?pid='123'&protokoll=1&wkid=4C50EFD222DB46D3892D31E10D573499"
        },
        {
            "date": "25.01.2014",
            "guest": "AC Mutterstadt",
            "home": "KSV Durlach",
            "location": "Karlsruhe-Durlach",
            "score": "756.4 : 673.5",
            "url": "https://www.iat.uni-leipzig.de/datenbanken/blgew1314/start.php?pid='123'&protokoll=1&wkid=AEDAD960E7334BF58FEDCD79F9DB606E"
        },
        {
            "date": "21.12.2013",
            "guest": "SV Germania Obrigheim",
            "home": "AV Speyer 03",
            "location": "Speyer",
            "score": "0.0 : 920.2",
            "url": "https://www.iat.uni-leipzig.de/datenbanken/blgew1314/start.php?pid='123'&protokoll=1&wkid=27B64CC3E5F64843A57B7CD5BC9BC298"
        },
        {
            "date": "21.12.2013",
            "guest": "TSV Heinsheim",
            "home": "KSV Durlach",
            "location": "Karlsruhe-Durlach",
            "score": "739.0 : 584.0",
            "url": "https://www.iat.uni-leipzig.de/datenbanken/blgew1314/start.php?pid='123'&protokoll=1&wkid=4D66CA45EA5B4D3480BFBEDA4530E004"
        },
        {
            "date": "21.12.2013",
            "guest": "AC Germania St.Ilgen",
            "home": "AC Mutterstadt",
            "location": "Mutterstadt",
            "score": "721.0 : 777.4",
            "url": "https://www.iat.uni-leipzig.de/datenbanken/blgew1314/start.php?pid='123'&protokoll=1&wkid=429360A6B99F4FCDA856B71532A28621"
        },
        {
            "date": "07.12.2013",
            "guest": "KSV Durlach",
            "home": "SV Germania Obrigheim",
            "location": "Obrigheim",
            "score": "900.4 : 603.2",
            "url": "https://www.iat.uni-leipzig.de/datenbanken/blgew1314/start.php?pid='123'&protokoll=1&wkid=0D74F8637F674C5894CE8C749E0C90A0"
        },
        {
            "date": "07.12.2013",
            "guest": "AV Speyer 03",
            "home": "TB 03 Roding",
            "location": "Roding",
            "score": "750.0 : 782.8",
            "url": "https://www.iat.uni-leipzig.de/datenbanken/blgew1314/start.php?pid='123'&protokoll=1&wkid=24398CA77B2D45F3AAB79F95421CA98C"
        },
        {
            "date": "07.12.2013",
            "guest": "AC Mutterstadt",
            "home": "TSV Heinsheim",
            "location": "Bad Rappenau",
            "score": "589.9 : 699.9",
            "url": "https://www.iat.uni-leipzig.de/datenbanken/blgew1314/start.php?pid='123'&protokoll=1&wkid=25EC0ACF577B474787F8C50B68F51BB2"
        },
        {
            "date": "23.11.2013",
            "guest": "AV Speyer 03",
            "home": "AC Mutterstadt",
            "location": "Mutterstadt",
            "score": "734.7 : 680.9",
            "url": "https://www.iat.uni-leipzig.de/datenbanken/blgew1314/start.php?pid='123'&protokoll=1&wkid=F4BC8BD1514A470DBFE01C2D4E9A0E6A"
        },
        {
            "date": "23.11.2013",
            "guest": "TB 03 Roding",
            "home": "TSV Heinsheim",
            "location": "Bad Rappenau",
            "score": "601.2 : 700.4",
            "url": "https://www.iat.uni-leipzig.de/datenbanken/blgew1314/start.php?pid='123'&protokoll=1&wkid=1DC1DF3C0E6C491E8C8BDC717765827C"
        },
        {
            "date": "23.11.2013",
            "guest": "SV Germania Obrigheim",
            "home": "AC Germania St.Ilgen",
            "location": "Leimen-St Ilgen",
            "score": "684.2 : 792.3",
            "url": "https://www.iat.uni-leipzig.de/datenbanken/blgew1314/start.php?pid='123'&protokoll=1&wkid=D81770DC88484D33B0DA7F818436E77A"
        },
        {
            "date": "09.11.2013",
            "guest": "AC Germania St.Ilgen",
            "home": "AV Speyer 03",
            "location": "Speyer",
            "score": "631.0 : 689.0",
            "url": "https://www.iat.uni-leipzig.de/datenbanken/blgew1314/start.php?pid='123'&protokoll=1&wkid=7F366F615AA04FC1B4C220AD00A5E5BE"
        },
        {
            "date": "09.11.2013",
            "guest": "TSV Heinsheim",
            "home": "SV Germania Obrigheim",
            "location": "Obrigheim",
            "score": "904.3 : 604.6",
            "url": "https://www.iat.uni-leipzig.de/datenbanken/blgew1314/start.php?pid='123'&protokoll=1&wkid=F615C2018C49458A95D78D682811E589"
        },
        {
            "date": "09.11.2013",
            "guest": "KSV Durlach",
            "home": "TB 03 Roding",
            "location": "Roding",
            "score": "704.8 : 733.6",
            "url": "https://www.iat.uni-leipzig.de/datenbanken/blgew1314/start.php?pid='123'&protokoll=1&wkid=94346D4C54834274AFD54B9E438CC1F4"
        },
        {
            "date": "12.10.2013",
            "guest": "SV Germania Obrigheim",
            "home": "AC Mutterstadt",
            "location": "Mutterstadt",
            "score": "722.4 : 870.4",
            "url": "https://www.iat.uni-leipzig.de/datenbanken/blgew1314/start.php?pid='123'&protokoll=1&wkid=4B72AB088FEA4752A376D56E4C74FCC2"
        },
        {
            "date": "12.10.2013",
            "guest": "AV Speyer 03",
            "home": "KSV Durlach",
            "location": "Karlsruhe-Durlach",
            "score": "725.0 : 741.8",
            "url": "https://www.iat.uni-leipzig.de/datenbanken/blgew1314/start.php?pid='123'&protokoll=1&wkid=B0C4573EF91A4A7DBFA14E2DBD5C5073"
        },
        {
            "date": "12.10.2013",
            "guest": "TB 03 Roding",
            "home": "AC Germania St.Ilgen",
            "location": "Leimen-St Ilgen",
            "score": "761.2 : 692.2",
            "url": "https://www.iat.uni-leipzig.de/datenbanken/blgew1314/start.php?pid='123'&protokoll=1&wkid=F469B9E9CA29421FADCDB540490D03D3"
        }
    ]
}]